PushySDK/__init__.py
PushySDK-0.1.5.dist-info/DESCRIPTION.rst
PushySDK-0.1.5.dist-info/METADATA
PushySDK-0.1.5.dist-info/RECORD
PushySDK-0.1.5.dist-info/WHEEL
PushySDK-0.1.5.dist-info/metadata.json
PushySDK-0.1.5.dist-info/top_level.txt
